ai/__init__.py
aiexpts/__init__.py
jodAI/__init__.py
jodAI-0.0.92.dist-info/Licence.txt.txt
jodAI-0.0.92.dist-info/METADATA
jodAI-0.0.92.dist-info/WHEEL
jodAI-0.0.92.dist-info/top_level.txt
jodAI-0.0.92.dist-info/RECORD
