Metadata-Version: 2.1
Name: jodAI
Version: 0.0.92
Summary: AI ke Expts hai
Author: Godfather
License: UNKNOWN
Platform: UNKNOWN
License-File: Licence.txt.txt
